SPLICE_q-1.0.0.data/scripts/SPLICE-q.py
spliceq/SPLICE-q.py
spliceq/__init__.py
SPLICE_q-1.0.0.dist-info/LICENSE
SPLICE_q-1.0.0.dist-info/METADATA
SPLICE_q-1.0.0.dist-info/WHEEL
SPLICE_q-1.0.0.dist-info/top_level.txt
SPLICE_q-1.0.0.dist-info/RECORD
