Metadata-Version: 2.1
Name: SPLICE-q
Version: 1.0.0
Summary: SPLICE-q is a fast and user-friendly Python tool for genome-wide SPLICing Efficiency quantification
Home-page: https://github.com/vrmelo/SPLICE-q
Author: Verônica R Melo Costa, Julianus Pfeuffer, Annita Louloupi, Ulf A V Ørom, Rosario M Piro
Author-email: veronica.melocosta@gmail.com
License: GPL-2
Platform: UNKNOWN
Classifier: Programming Language :: Python :: 3
Classifier: License :: OSI Approved :: GNU General Public License v2 (GPLv2)
Classifier: Operating System :: OS Independent
Requires-Python: >=3.6
Requires-Dist: pysam
Requires-Dist: rich
Requires-Dist: interlap
Requires-Dist: numpy
